eats/__init__.py
eats/constants.py
eats/decorators.py
eats/exceptions.py
eats/lookups.py
eats/urls.py
eats/forms/__init__.py
eats/forms/admin.py
eats/forms/admin_model.py
eats/forms/display.py
eats/forms/edit.py
eats/lib/__init__.py
eats/lib/eatsml_exporter.py
eats/lib/eatsml_handler.py
eats/lib/eatsml_importer.py
eats/lib/name_form.py
eats/lib/property_assertions.py
eats/lib/user.py
eats/lib/views.py
eats/management/__init__.py
eats/management/commands/__init__.py
eats/management/commands/eats_reindex.py
eats/migrations/0001_initial.py
eats/migrations/__init__.py
eats/models/__init__.py
eats/models/authority.py
eats/models/base_manager.py
eats/models/calendar.py
eats/models/date.py
eats/models/date_part.py
eats/models/date_period.py
eats/models/date_type.py
eats/models/eats_topic_map.py
eats/models/eats_user.py
eats/models/eatsml_import.py
eats/models/entity.py
eats/models/entity_relationship_cache.py
eats/models/entity_relationship_property_assertion.py
eats/models/entity_relationship_type.py
eats/models/entity_type.py
eats/models/entity_type_property_assertion.py
eats/models/existence_property_assertion.py
eats/models/infrastructure.py
eats/models/infrastructure_manager.py
eats/models/language.py
eats/models/name.py
eats/models/name_cache.py
eats/models/name_element.py
eats/models/name_index.py
eats/models/name_part.py
eats/models/name_part_type.py
eats/models/name_property_assertion.py
eats/models/name_type.py
eats/models/note_property_assertion.py
eats/models/property_assertion.py
eats/models/script.py
eats/models/subject_identifier_property_assertion.py
eats/templatetags/__init__.py
eats/templatetags/entity_display.py
eats/tests/__init__.py
eats/tests/base_test_case.py
eats/tests/test_eatsml_export.py
eats/tests/test_eatsml_import.py
eats/tests/test_lookups.py
eats/tests/test_name_form.py
eats/tests/test_property_assertions.py
eats/tests/models/__init__.py
eats/tests/models/model_test_case.py
eats-1.0.0.dist-info/DESCRIPTION.rst
eats-1.0.0.dist-info/METADATA
eats-1.0.0.dist-info/RECORD
eats-1.0.0.dist-info/WHEEL
eats-1.0.0.dist-info/metadata.json
eats-1.0.0.dist-info/top_level.txt
