Metadata-Version: 2.0
Name: eats
Version: 1.0.0
Summary: Django app for recording, editing, using and displaying authority information about entities.
Home-page: https://github.com/ajenhl/eats
Author: Jamie Norrish
Author-email: jamie@artefact.org.nz
License: GNU General Public License v3
Platform: UNKNOWN
Classifier: Framework :: Django
Classifier: License :: OSI Approved :: GNU General Public License v3 (GPLv3)
Classifier: Programming Language :: Python
Classifier: Programming Language :: Python :: 3 :: Only
Requires-Dist: Django (>=1.8)
Requires-Dist: django-selectable
Requires-Dist: django-tmapi
Requires-Dist: lxml
